[
  {
    "key": "安徽省/安庆市/太湖县",
    "govUrl": "http://www.thx.gov.cn/",
    "reason": "no-disclosure-route"
  },
  {
    "key": "安徽省/安庆市/宜秀区",
    "govUrl": "https://www.yixiu.gov.cn/",
    "reason": "no-disclosure-route"
  },
  {
    "key": "安徽省/蚌埠市/怀远县",
    "govUrl": "https://www.ahhy.gov.cn/",
    "picked": {
      "url": "https://www.ahhy.gov.cn/zfxxgk/public/column/29621?type=2&publicType=gkzn",
      "text": "政府信息公开",
      "score": 102,
      "source": "anchor",
      "validated": true
    }
  },
  {
    "key": "安徽省/蚌埠市/龙子湖区",
    "govUrl": "https://www.bblzh.gov.cn/",
    "picked": {
      "url": "https://www.bblzh.gov.cn/zfxxgk/public/column/29571?type=2&publicType=gkzn",
      "text": "政府信息公开",
      "score": 102,
      "source": "anchor",
      "validated": true
    }
  },
  {
    "key": "安徽省/亳州市",
    "govUrl": "http://www.bozhou.gov.cn/",
    "reason": "no-disclosure-route"
  },
  {
    "key": "安徽省/亳州市/利辛县",
    "govUrl": "https://www.lixin.gov.cn/",
    "reason": "no-disclosure-route"
  },
  {
    "key": "安徽省/亳州市/蒙城县",
    "govUrl": "https://www.mengcheng.gov.cn/",
    "reason": "no-disclosure-route"
  },
  {
    "key": "安徽省/亳州市/谯城区",
    "govUrl": "https://www.bzqc.gov.cn/",
    "reason": "no-disclosure-route"
  },
  {
    "key": "安徽省/亳州市/涡阳县",
    "govUrl": "http://www.gy.gov.cn/",
    "reason": "no-disclosure-route"
  },
  {
    "key": "安徽省/滁州市/天长市",
    "govUrl": "http://www.tianchang.gov.cn/",
    "reason": "no-disclosure-route"
  },
  {
    "key": "安徽省/阜阳市/阜南县",
    "govUrl": "https://www.funan.gov.cn/",
    "reason": "homepage-unreachable"
  },
  {
    "key": "安徽省/合肥市/包河区",
    "govUrl": "https://www.baohe.gov.cn/",
    "reason": "homepage-unreachable"
  },
  {
    "key": "安徽省/合肥市/巢湖市",
    "govUrl": "https://www.chaohu.gov.cn/",
    "reason": "homepage-unreachable"
  },
  {
    "key": "安徽省/合肥市/肥东县",
    "govUrl": "https://www.feidong.gov.cn/",
    "reason": "homepage-unreachable"
  },
  {
    "key": "安徽省/合肥市/肥西县",
    "govUrl": "https://www.ahfeixi.gov.cn/",
    "reason": "homepage-unreachable"
  },
  {
    "key": "安徽省/合肥市/庐江县",
    "govUrl": "https://www.lj.gov.cn/",
    "reason": "homepage-unreachable"
  },
  {
    "key": "安徽省/合肥市/庐阳区",
    "govUrl": "https://www.ahhfly.gov.cn/",
    "reason": "homepage-unreachable"
  },
  {
    "key": "安徽省/合肥市/蜀山区",
    "govUrl": "https://www.hfss.gov.cn/",
    "reason": "homepage-unreachable"
  },
  {
    "key": "安徽省/合肥市/长丰县",
    "govUrl": "https://www.changfeng.gov.cn/",
    "reason": "homepage-unreachable"
  },
  {
    "key": "安徽省/淮南市/大通区",
    "govUrl": "https://www.hndt.gov.cn/",
    "reason": "no-disclosure-route"
  },
  {
    "key": "安徽省/淮南市/凤台县",
    "govUrl": "https://www.ft.gov.cn/",
    "reason": "no-disclosure-route"
  },
  {
    "key": "安徽省/淮南市/寿县",
    "govUrl": "https://www.shouxian.gov.cn/",
    "reason": "no-disclosure-route"
  },
  {
    "key": "安徽省/黄山市/黄山区",
    "govUrl": "https://www.hsq.gov.cn/",
    "reason": "homepage-unreachable"
  },
  {
    "key": "安徽省/黄山市/徽州区",
    "govUrl": "https://www.ahhz.gov.cn/",
    "reason": "homepage-unreachable"
  },
  {
    "key": "安徽省/黄山市/祁门县",
    "govUrl": "https://www.ahqimen.gov.cn/",
    "reason": "homepage-unreachable"
  },
  {
    "key": "安徽省/黄山市/歙县",
    "govUrl": "https://www.ahshx.gov.cn/",
    "reason": "homepage-unreachable"
  },
  {
    "key": "安徽省/黄山市/休宁县",
    "govUrl": "https://www.xiuning.gov.cn/",
    "reason": "homepage-unreachable"
  },
  {
    "key": "安徽省/黄山市/黟县",
    "govUrl": "https://www.yixian.gov.cn/",
    "reason": "homepage-unreachable"
  },
  {
    "key": "安徽省/宣城市/广德市",
    "govUrl": "https://www.guangde.gov.cn/",
    "picked": {
      "url": "https://www.guangde.gov.cn/OpennessFinance/",
      "text": "财政预决算三公经费 政府信息公开",
      "score": 72,
      "source": "anchor",
      "validated": true
    }
  },
  {
    "key": "安徽省/宣城市/宣州区",
    "govUrl": "https://www.xuanzhou.gov.cn/",
    "reason": "no-disclosure-route"
  },
  {
    "key": "北京市/朝阳区",
    "govUrl": "http://www.bjchy.gov.cn/",
    "reason": "no-disclosure-route"
  },
  {
    "key": "甘肃省/白银市/景泰县",
    "govUrl": "https://www.jingtai.gov.cn/",
    "reason": "homepage-unreachable"
  },
  {
    "key": "甘肃省/定西市/安定区",
    "govUrl": "http://www.anding.gov.cn/",
    "reason": "no-disclosure-route"
  },
  {
    "key": "甘肃省/定西市/临洮县",
    "govUrl": "http://www.lintao.gov.cn/",
    "reason": "no-disclosure-route"
  },
  {
    "key": "甘肃省/定西市/通渭县",
    "govUrl": "http://www.tongwei.gov.cn/",
    "reason": "no-disclosure-route"
  },
  {
    "key": "甘肃省/酒泉市/阿克塞哈萨克族自治县",
    "govUrl": "http://www.akesai.gov.cn/",
    "reason": "no-disclosure-route"
  },
  {
    "key": "甘肃省/酒泉市/敦煌市",
    "govUrl": "http://www.dunhuang.gov.cn/",
    "reason": "no-disclosure-route"
  },
  {
    "key": "甘肃省/兰州市/城关区",
    "govUrl": "https://www.lzcgq.gov.cn/",
    "reason": "no-disclosure-route"
  },
  {
    "key": "甘肃省/兰州市/皋兰县",
    "govUrl": "http://www.gaolan.gov.cn/",
    "reason": "no-disclosure-route"
  },
  {
    "key": "甘肃省/兰州市/红古区",
    "govUrl": "https://www.honggu.gov.cn/",
    "reason": "no-disclosure-route"
  },
  {
    "key": "甘肃省/兰州市/七里河区",
    "govUrl": "http://www.qilihe.gov.cn/",
    "reason": "no-disclosure-route"
  },
  {
    "key": "甘肃省/兰州市/永登县",
    "govUrl": "http://www.yongdeng.gov.cn/",
    "reason": "no-disclosure-route"
  },
  {
    "key": "甘肃省/兰州市/榆中县",
    "govUrl": "https://www.lzyuzhong.gov.cn/",
    "reason": "no-disclosure-route"
  },
  {
    "key": "甘肃省/临夏回族自治州/临夏县",
    "govUrl": "https://www.linxiaxian.gov.cn/",
    "reason": "no-disclosure-route"
  },
  {
    "key": "广东省/揭阳市/揭东区",
    "govUrl": "http://www.jiedong.gov.cn/",
    "reason": "no-disclosure-route"
  },
  {
    "key": "广东省/清远市",
    "govUrl": "http://www.gdqy.gov.cn/",
    "reason": "homepage-unreachable"
  },
  {
    "key": "广东省/韶关市/乐昌市",
    "govUrl": "https://www.lechang.gov.cn/",
    "reason": "homepage-unreachable"
  },
  {
    "key": "广东省/韶关市/始兴县",
    "govUrl": "https://www.gdsx.gov.cn/",
    "reason": "homepage-unreachable"
  },
  {
    "key": "广东省/珠海市/斗门区",
    "govUrl": "https://www.doumen.gov.cn/",
    "reason": "no-disclosure-route"
  },
  {
    "key": "广东省/珠海市/金湾区",
    "govUrl": "https://www.jinwan.gov.cn/",
    "reason": "no-disclosure-route"
  },
  {
    "key": "广西壮族自治区/桂林市/阳朔县",
    "govUrl": "http://www.yangshuo.gov.cn/",
    "reason": "no-disclosure-route"
  },
  {
    "key": "广西壮族自治区/贺州市/富川瑶族自治县",
    "govUrl": "http://www.gxfc.gov.cn/",
    "reason": "no-disclosure-route"
  },
  {
    "key": "贵州省/毕节市/七星关区",
    "govUrl": "http://www.bjqixingguan.gov.cn/",
    "reason": "no-disclosure-route"
  },
  {
    "key": "贵州省/铜仁市",
    "govUrl": "https://www.tongren.gov.cn/",
    "reason": "no-disclosure-route"
  },
  {
    "key": "河北省/保定市/安国市",
    "govUrl": "http://www.anguo.gov.cn/",
    "reason": "no-disclosure-route"
  },
  {
    "key": "河北省/保定市/定州市",
    "govUrl": "http://www.dzs.gov.cn/",
    "reason": "no-disclosure-route"
  },
  {
    "key": "河北省/保定市/阜平县",
    "govUrl": "https://www.bdfuping.gov.cn/",
    "reason": "no-disclosure-route"
  },
  {
    "key": "河北省/保定市/顺平县",
    "govUrl": "http://www.shunping.gov.cn/",
    "reason": "no-disclosure-route"
  },
  {
    "key": "河北省/保定市/望都县",
    "govUrl": "http://www.wangdu.gov.cn/",
    "reason": "no-disclosure-route"
  },
  {
    "key": "河北省/保定市/易县",
    "govUrl": "https://www.bdyixian.gov.cn/",
    "reason": "no-disclosure-route"
  },
  {
    "key": "河北省/承德市/鹰手营子矿区",
    "govUrl": "http://www.ysyz.gov.cn/",
    "reason": "no-disclosure-route"
  },
  {
    "key": "河北省/邯郸市/成安县",
    "govUrl": "https://www.chengan.gov.cn/",
    "reason": "no-disclosure-route"
  },
  {
    "key": "河北省/邯郸市/磁县",
    "govUrl": "http://www.cixian.gov.cn/",
    "reason": "no-disclosure-route"
  },
  {
    "key": "河北省/邯郸市/丛台区",
    "govUrl": "http://www.hdct.gov.cn/",
    "reason": "no-disclosure-route"
  },
  {
    "key": "河北省/邯郸市/肥乡区",
    "govUrl": "https://www.fxq.gov.cn/",
    "reason": "no-disclosure-route"
  },
  {
    "key": "河北省/邯郸市/鸡泽县",
    "govUrl": "http://www.jize.gov.cn/",
    "reason": "no-disclosure-route"
  },
  {
    "key": "河北省/邯郸市/曲周县",
    "govUrl": "http://www.qzx.gov.cn/",
    "reason": "no-disclosure-route"
  },
  {
    "key": "河北省/衡水市/安平县",
    "govUrl": "http://www.anping.gov.cn/",
    "reason": "no-disclosure-route"
  },
  {
    "key": "河北省/衡水市/冀州区",
    "govUrl": "http://www.jizhou.gov.cn/",
    "reason": "no-disclosure-route"
  },
  {
    "key": "河北省/衡水市/景县",
    "govUrl": "http://www.jingxian.gov.cn/",
    "reason": "no-disclosure-route"
  },
  {
    "key": "河北省/衡水市/饶阳县",
    "govUrl": "http://www.raoyang.gov.cn/",
    "reason": "no-disclosure-route"
  },
  {
    "key": "河北省/衡水市/深州市",
    "govUrl": "http://www.shenzhou.gov.cn/",
    "reason": "no-disclosure-route"
  },
  {
    "key": "河北省/衡水市/桃城区",
    "govUrl": "http://www.taocheng.gov.cn/",
    "reason": "no-disclosure-route"
  },
  {
    "key": "河北省/衡水市/武强县",
    "govUrl": "http://www.wuqiang.gov.cn/",
    "reason": "no-disclosure-route"
  },
  {
    "key": "河北省/衡水市/枣强县",
    "govUrl": "http://www.zaoqiang.gov.cn/",
    "reason": "no-disclosure-route"
  },
  {
    "key": "河北省/廊坊市/安次区",
    "govUrl": "https://www.anci.gov.cn/",
    "reason": "homepage-unreachable"
  },
  {
    "key": "河北省/廊坊市/大厂回族自治县",
    "govUrl": "https://www.lfdc.gov.cn/",
    "reason": "no-disclosure-route"
  },
  {
    "key": "河北省/廊坊市/大城县",
    "govUrl": "https://www.dacheng.gov.cn/",
    "reason": "no-disclosure-route"
  },
  {
    "key": "河北省/廊坊市/固安县",
    "govUrl": "http://www.guan.gov.cn/",
    "reason": "homepage-unreachable"
  },
  {
    "key": "河北省/廊坊市/文安县",
    "govUrl": "http://www.wenan.gov.cn/",
    "reason": "no-disclosure-route"
  },
  {
    "key": "河北省/廊坊市/香河县",
    "govUrl": "http://www.xianghe.gov.cn/",
    "reason": "no-disclosure-route"
  },
  {
    "key": "河北省/秦皇岛市/卢龙县",
    "govUrl": "https://www.lulong.gov.cn/",
    "reason": "homepage-unreachable"
  },
  {
    "key": "河北省/石家庄市/裕华区",
    "govUrl": "http://www.yuhuaqu.gov.cn/",
    "reason": "no-disclosure-route"
  },
  {
    "key": "河北省/石家庄市/赞皇县",
    "govUrl": "http://www.zanhuang.gov.cn/",
    "reason": "no-disclosure-route"
  },
  {
    "key": "河北省/唐山市",
    "govUrl": "https://www.tangshan.gov.cn/",
    "reason": "homepage-unreachable"
  },
  {
    "key": "河北省/唐山市/丰南区",
    "govUrl": "https://www.fengnanqu.gov.cn/",
    "reason": "no-disclosure-route"
  },
  {
    "key": "河北省/唐山市/滦州市",
    "govUrl": "http://www.luanxian.gov.cn/",
    "reason": "homepage-unreachable"
  },
  {
    "key": "河南省/安阳市/内黄县",
    "govUrl": "http://www.neihuang.gov.cn/",
    "reason": "no-disclosure-route"
  },
  {
    "key": "河南省/鹤壁市",
    "govUrl": "https://www.hebi.gov.cn/",
    "reason": "homepage-unreachable"
  },
  {
    "key": "河南省/鹤壁市/浚县",
    "govUrl": "https://www.xunxian.gov.cn/",
    "reason": "homepage-unreachable"
  },
  {
    "key": "河南省/鹤壁市/淇县",
    "govUrl": "http://www.qxzf.gov.cn/",
    "reason": "homepage-unreachable"
  },
  {
    "key": "河南省/平顶山市/郏县",
    "govUrl": "http://www.jiaxian.gov.cn/",
    "reason": "no-disclosure-route"
  },
  {
    "key": "河南省/平顶山市/石龙区",
    "govUrl": "https://www.shilongqu.gov.cn/",
    "reason": "no-disclosure-route"
  },
  {
    "key": "河南省/濮阳市/范县",
    "govUrl": "http://www.fanxian.gov.cn/",
    "reason": "no-disclosure-route"
  },
  {
    "key": "河南省/濮阳市/清丰县",
    "govUrl": "http://www.qingfeng.gov.cn/",
    "reason": "homepage-unreachable"
  },
  {
    "key": "河南省/三门峡市/卢氏县",
    "govUrl": "https://www.lushixian.gov.cn/",
    "reason": "no-disclosure-route"
  },
  {
    "key": "河南省/三门峡市/渑池县",
    "govUrl": "https://www.mianchi.gov.cn/",
    "reason": "no-disclosure-route"
  },
  {
    "key": "河南省/商丘市/柘城县",
    "govUrl": "https://www.zhecheng.gov.cn/",
    "reason": "homepage-unreachable"
  },
  {
    "key": "河南省/新乡市/新乡县",
    "govUrl": "http://www.xinxiangxian.gov.cn/",
    "picked": {
      "url": "http://www.xinxiangxian.gov.cn/htmls/30mc64uz_fadingzhudonggongkaineirong/list-1.html",
      "text": "--> 法定主动公开内容",
      "score": 75,
      "source": "anchor",
      "validated": true
    }
  },
  {
    "key": "河南省/周口市/郸城县",
    "govUrl": "http://www.dancheng.gov.cn/",
    "reason": "no-disclosure-route"
  },
  {
    "key": "黑龙江省/大庆市/让胡路区",
    "govUrl": "http://www.dqrhl.gov.cn/",
    "reason": "no-disclosure-route"
  },
  {
    "key": "黑龙江省/大庆市/肇州县",
    "govUrl": "http://www.zhaozhou.gov.cn/",
    "reason": "no-disclosure-route"
  },
  {
    "key": "黑龙江省/哈尔滨市/宾县",
    "govUrl": "http://www.chinabx.gov.cn/",
    "reason": "no-disclosure-route"
  },
  {
    "key": "黑龙江省/黑河市",
    "govUrl": "https://www.heihe.gov.cn/",
    "reason": "no-disclosure-route"
  },
  {
    "key": "黑龙江省/黑河市/五大连池市",
    "govUrl": "https://www.wdlc.gov.cn/",
    "reason": "no-disclosure-route"
  },
  {
    "key": "黑龙江省/鸡西市",
    "govUrl": "https://www.jixi.gov.cn/",
    "picked": {
      "url": "https://www.jixi.gov.cn/jixi/c100117/common_zfxxgk.shtml?tab=gkzn",
      "text": "政府信息公开",
      "score": 90,
      "source": "anchor",
      "validated": true
    }
  },
  {
    "key": "黑龙江省/鸡西市/城子河区",
    "govUrl": "https://www.czh.gov.cn/",
    "reason": "no-disclosure-route"
  },
  {
    "key": "黑龙江省/鸡西市/滴道区",
    "govUrl": "http://www.didaoqu.gov.cn/",
    "reason": "no-disclosure-route"
  },
  {
    "key": "黑龙江省/鸡西市/恒山区",
    "govUrl": "https://www.jixihengshan.gov.cn/",
    "reason": "no-disclosure-route"
  },
  {
    "key": "黑龙江省/鸡西市/鸡冠区",
    "govUrl": "https://www.jgq.gov.cn/",
    "reason": "no-disclosure-route"
  },
  {
    "key": "黑龙江省/鸡西市/梨树区",
    "govUrl": "https://jixilishu.gov.cn/",
    "reason": "no-disclosure-route"
  },
  {
    "key": "黑龙江省/鸡西市/麻山区",
    "govUrl": "https://www.jiximashan.gov.cn/",
    "reason": "no-disclosure-route"
  },
  {
    "key": "黑龙江省/鸡西市/密山市",
    "govUrl": "http://hljms.gov.cn/",
    "reason": "no-disclosure-route"
  },
  {
    "key": "黑龙江省/七台河市",
    "govUrl": "https://www.qth.gov.cn/",
    "reason": "no-disclosure-route"
  },
  {
    "key": "黑龙江省/七台河市/勃利县",
    "govUrl": "http://www.hljboli.gov.cn/",
    "reason": "no-disclosure-route"
  },
  {
    "key": "黑龙江省/七台河市/茄子河区",
    "govUrl": "http://www.hljqzh.gov.cn/",
    "reason": "no-disclosure-route"
  },
  {
    "key": "黑龙江省/七台河市/桃山区",
    "govUrl": "http://www.hljtsq.gov.cn/",
    "reason": "no-disclosure-route"
  },
  {
    "key": "黑龙江省/七台河市/新兴区",
    "govUrl": "http://www.hljxinxing.gov.cn/",
    "reason": "no-disclosure-route"
  },
  {
    "key": "黑龙江省/双鸭山市/宝清县",
    "govUrl": "https://hlbaoqing.gov.cn/",
    "reason": "no-disclosure-route"
  },
  {
    "key": "黑龙江省/绥化市",
    "govUrl": "https://www.suihua.gov.cn/",
    "reason": "homepage-unreachable"
  },
  {
    "key": "黑龙江省/绥化市/安达市",
    "govUrl": "http://www.hlanda.gov.cn/",
    "reason": "no-disclosure-route"
  },
  {
    "key": "黑龙江省/绥化市/海伦市",
    "govUrl": "http://www.hailun.gov.cn/",
    "reason": "no-disclosure-route"
  },
  {
    "key": "黑龙江省/绥化市/兰西县",
    "govUrl": "https://www.hljlanxi.gov.cn/",
    "reason": "no-disclosure-route"
  },
  {
    "key": "黑龙江省/绥化市/明水县",
    "govUrl": "http://www.mingshui.gov.cn/",
    "reason": "no-disclosure-route"
  },
  {
    "key": "黑龙江省/绥化市/青冈县",
    "govUrl": "https://www.qgnet.gov.cn/",
    "reason": "no-disclosure-route"
  },
  {
    "key": "黑龙江省/绥化市/绥棱县",
    "govUrl": "http://www.suiling.gov.cn/",
    "reason": "no-disclosure-route"
  },
  {
    "key": "黑龙江省/绥化市/肇东市",
    "govUrl": "https://www.hljzhaodong.gov.cn/",
    "reason": "no-disclosure-route"
  },
  {
    "key": "黑龙江省/伊春市/乌翠区",
    "govUrl": "http://www.ycwc.gov.cn/",
    "reason": "homepage-unreachable"
  },
  {
    "key": "湖北省/鄂州市/华容区",
    "govUrl": "https://www.hbhr.gov.cn/",
    "reason": "no-disclosure-route"
  },
  {
    "key": "湖北省/恩施土家族苗族自治州/咸丰县",
    "govUrl": "http://www.xianfeng.gov.cn/",
    "reason": "no-disclosure-route"
  },
  {
    "key": "湖北省/黄冈市/罗田县",
    "govUrl": "http://www.luotian.gov.cn/",
    "reason": "no-disclosure-route"
  },
  {
    "key": "湖北省/黄冈市/团风县",
    "govUrl": "http://www.tfzf.gov.cn/",
    "reason": "no-disclosure-route"
  },
  {
    "key": "湖北省/黄冈市/武穴市",
    "govUrl": "http://www.wuxue.gov.cn/",
    "reason": "no-disclosure-route"
  },
  {
    "key": "湖北省/黄冈市/英山县",
    "govUrl": "http://www.chinays.gov.cn/",
    "reason": "no-disclosure-route"
  },
  {
    "key": "湖北省/黄石市/铁山区",
    "govUrl": "https://www.hsdz.gov.cn/",
    "reason": "no-disclosure-route"
  },
  {
    "key": "湖北省/黄石市/下陆区",
    "govUrl": "https://www.xialuqu.gov.cn/",
    "reason": "no-disclosure-route"
  },
  {
    "key": "湖北省/荆州市/荆州区",
    "govUrl": "http://www.jingzhouqu.gov.cn/",
    "reason": "no-disclosure-route"
  },
  {
    "key": "湖北省/荆州市/石首市",
    "govUrl": "http://www.shishou.gov.cn/",
    "reason": "no-disclosure-route"
  },
  {
    "key": "湖北省/神农架林区",
    "govUrl": "http://www.snj.gov.cn/",
    "picked": {
      "url": "http://www.snj.gov.cn/zwgk/xxgkml/jgzn/",
      "text": "法定主动公开",
      "score": 87,
      "source": "anchor",
      "validated": true
    }
  },
  {
    "key": "湖北省/十堰市/茅箭区",
    "govUrl": "http://maojian.shiyan.gov.cn/",
    "reason": "no-disclosure-route"
  },
  {
    "key": "湖北省/十堰市/郧西县",
    "govUrl": "http://www.yunxi.gov.cn/",
    "reason": "no-disclosure-route"
  },
  {
    "key": "湖北省/十堰市/竹山县",
    "govUrl": "http://www.zhushan.gov.cn/",
    "reason": "no-disclosure-route"
  },
  {
    "key": "湖北省/十堰市/竹溪县",
    "govUrl": "http://www.zhuxi.gov.cn/",
    "reason": "no-disclosure-route"
  },
  {
    "key": "湖北省/随州市/随县",
    "govUrl": "http://www.zgsuixian.gov.cn/",
    "reason": "no-disclosure-route"
  },
  {
    "key": "湖北省/武汉市/蔡甸区",
    "govUrl": "https://www.caidian.gov.cn/",
    "reason": "no-disclosure-route"
  },
  {
    "key": "湖北省/武汉市/江汉区",
    "govUrl": "https://www.jianghan.gov.cn/",
    "reason": "no-disclosure-route"
  },
  {
    "key": "湖北省/武汉市/江夏区",
    "govUrl": "https://www.jiangxia.gov.cn/",
    "reason": "no-disclosure-route"
  },
  {
    "key": "湖北省/咸宁市/崇阳县",
    "govUrl": "http://chongyang.gov.cn/",
    "reason": "no-disclosure-route"
  },
  {
    "key": "湖北省/咸宁市/嘉鱼县",
    "govUrl": "http://www.jiayu.gov.cn/",
    "reason": "no-disclosure-route"
  },
  {
    "key": "湖北省/咸宁市/咸安区",
    "govUrl": "http://www.xianan.gov.cn/",
    "reason": "no-disclosure-route"
  },
  {
    "key": "湖北省/襄阳市",
    "govUrl": "https://www.xiangyang.gov.cn/",
    "reason": "homepage-unreachable"
  },
  {
    "key": "湖北省/襄阳市/保康县",
    "govUrl": "https://www.baokang.gov.cn/",
    "reason": "no-disclosure-route"
  },
  {
    "key": "湖北省/襄阳市/樊城区",
    "govUrl": "http://www.fc.gov.cn/",
    "reason": "no-disclosure-route"
  },
  {
    "key": "湖北省/襄阳市/谷城县",
    "govUrl": "http://www.hbgucheng.gov.cn/",
    "reason": "no-disclosure-route"
  },
  {
    "key": "湖北省/襄阳市/南漳县",
    "govUrl": "http://www.hbnz.gov.cn/",
    "reason": "no-disclosure-route"
  },
  {
    "key": "湖北省/襄阳市/宜城市",
    "govUrl": "http://ych.gov.cn/",
    "reason": "no-disclosure-route"
  },
  {
    "key": "湖北省/孝感市/大悟县",
    "govUrl": "http://www.hbdawu.gov.cn/",
    "reason": "no-disclosure-route"
  },
  {
    "key": "湖北省/孝感市/汉川市",
    "govUrl": "http://www.hanchuan.gov.cn/",
    "reason": "no-disclosure-route"
  },
  {
    "key": "湖北省/孝感市/云梦县",
    "govUrl": "http://www.yunmeng.gov.cn/",
    "reason": "no-disclosure-route"
  },
  {
    "key": "湖南省/郴州市",
    "govUrl": "https://www.czs.gov.cn/",
    "reason": "no-disclosure-route"
  },
  {
    "key": "湖南省/郴州市/安仁县",
    "govUrl": "http://www.anrenzf.gov.cn/",
    "reason": "homepage-unreachable"
  },
  {
    "key": "湖南省/郴州市/北湖区",
    "govUrl": "http://www.czbeihu.gov.cn/",
    "reason": "homepage-unreachable"
  },
  {
    "key": "湖南省/郴州市/桂东县",
    "govUrl": "http://www.gdx.gov.cn/",
    "reason": "homepage-unreachable"
  },
  {
    "key": "湖南省/郴州市/桂阳县",
    "govUrl": "http://www.hngy.gov.cn/",
    "reason": "homepage-unreachable"
  },
  {
    "key": "湖南省/郴州市/嘉禾县",
    "govUrl": "http://www.hnjh.gov.cn/",
    "reason": "homepage-unreachable"
  },
  {
    "key": "湖南省/郴州市/临武县",
    "govUrl": "http://www.lwx.gov.cn/",
    "reason": "homepage-unreachable"
  },
  {
    "key": "湖南省/郴州市/汝城县",
    "govUrl": "http://www.rc.gov.cn/",
    "reason": "homepage-unreachable"
  },
  {
    "key": "湖南省/郴州市/苏仙区",
    "govUrl": "http://www.hnsx.gov.cn/",
    "reason": "homepage-unreachable"
  },
  {
    "key": "湖南省/郴州市/宜章县",
    "govUrl": "http://www.yzx.gov.cn/",
    "reason": "homepage-unreachable"
  },
  {
    "key": "湖南省/郴州市/永兴县",
    "govUrl": "http://www.yxx.gov.cn/",
    "reason": "homepage-unreachable"
  },
  {
    "key": "湖南省/郴州市/资兴市",
    "govUrl": "https://www.zixing.gov.cn/",
    "reason": "no-disclosure-route"
  },
  {
    "key": "湖南省/怀化市/辰溪县",
    "govUrl": "https://www.chenxi.gov.cn/",
    "reason": "no-disclosure-route"
  },
  {
    "key": "湖南省/怀化市/鹤城区",
    "govUrl": "https://www.hechengqu.gov.cn/",
    "reason": "no-disclosure-route"
  },
  {
    "key": "湖南省/怀化市/麻阳苗族自治县",
    "govUrl": "https://www.mayang.gov.cn/",
    "reason": "no-disclosure-route"
  },
  {
    "key": "湖南省/怀化市/沅陵县",
    "govUrl": "https://www.yuanling.gov.cn/",
    "reason": "no-disclosure-route"
  },
  {
    "key": "湖南省/怀化市/芷江侗族自治县",
    "govUrl": "http://www.chnzj.gov.cn/",
    "reason": "no-disclosure-route"
  },
  {
    "key": "湖南省/怀化市/中方县",
    "govUrl": "http://www.zhongfang.gov.cn/",
    "reason": "no-disclosure-route"
  },
  {
    "key": "湖南省/邵阳市",
    "govUrl": "https://www.shaoyang.gov.cn/",
    "reason": "no-disclosure-route"
  },
  {
    "key": "湖南省/邵阳市/城步苗族自治县",
    "govUrl": "http://www.chengbu.gov.cn/",
    "reason": "no-disclosure-route"
  },
  {
    "key": "湖南省/邵阳市/邵阳县",
    "govUrl": "http://www.syx.gov.cn/",
    "reason": "no-disclosure-route"
  },
  {
    "key": "湖南省/邵阳市/双清区",
    "govUrl": "https://www.shuangqing.gov.cn/",
    "reason": "no-disclosure-route"
  },
  {
    "key": "湖南省/邵阳市/新宁县",
    "govUrl": "http://www.xinning.gov.cn/",
    "reason": "no-disclosure-route"
  },
  {
    "key": "湖南省/湘潭市",
    "govUrl": "https://www.xiangtan.gov.cn/",
    "reason": "no-disclosure-route"
  },
  {
    "key": "湖南省/湘潭市/韶山市",
    "govUrl": "https://www.shaoshan.gov.cn/",
    "reason": "no-disclosure-route"
  },
  {
    "key": "湖南省/湘潭市/湘潭县",
    "govUrl": "http://www.xtx.gov.cn/",
    "reason": "no-disclosure-route"
  },
  {
    "key": "湖南省/湘潭市/湘乡市",
    "govUrl": "http://www.xxs.gov.cn/",
    "reason": "no-disclosure-route"
  },
  {
    "key": "湖南省/湘潭市/雨湖区",
    "govUrl": "http://www.xtyh.gov.cn/",
    "reason": "no-disclosure-route"
  },
  {
    "key": "湖南省/湘潭市/岳塘区",
    "govUrl": "http://www.hnxtyt.gov.cn/",
    "reason": "no-disclosure-route"
  },
  {
    "key": "湖南省/湘西土家族苗族自治州",
    "govUrl": "https://www.xxz.gov.cn/",
    "reason": "homepage-unreachable"
  },
  {
    "key": "湖南省/湘西土家族苗族自治州/保靖县",
    "govUrl": "http://www.bjzf.gov.cn/",
    "reason": "homepage-unreachable"
  },
  {
    "key": "湖南省/湘西土家族苗族自治州/凤凰县",
    "govUrl": "http://www.fhzf.gov.cn/",
    "reason": "homepage-unreachable"
  },
  {
    "key": "湖南省/湘西土家族苗族自治州/古丈县",
    "govUrl": "http://www.guzhang.gov.cn/",
    "reason": "homepage-unreachable"
  },
  {
    "key": "湖南省/湘西土家族苗族自治州/花垣县",
    "govUrl": "http://www.huayuan.gov.cn/",
    "reason": "homepage-unreachable"
  },
  {
    "key": "湖南省/湘西土家族苗族自治州/吉首市",
    "govUrl": "http://www.jishou.gov.cn/",
    "reason": "homepage-unreachable"
  },
  {
    "key": "湖南省/湘西土家族苗族自治州/龙山县",
    "govUrl": "http://www.xxls.gov.cn/",
    "reason": "homepage-unreachable"
  },
  {
    "key": "湖南省/湘西土家族苗族自治州/泸溪县",
    "govUrl": "http://www.lxx.gov.cn/",
    "reason": "homepage-unreachable"
  },
  {
    "key": "湖南省/湘西土家族苗族自治州/永顺县",
    "govUrl": "http://www.ysx.gov.cn/",
    "reason": "homepage-unreachable"
  },
  {
    "key": "湖南省/益阳市",
    "govUrl": "https://www.yiyang.gov.cn/",
    "reason": "no-disclosure-route"
  },
  {
    "key": "湖南省/益阳市/安化县",
    "govUrl": "http://www.anhua.gov.cn/",
    "reason": "no-disclosure-route"
  },
  {
    "key": "湖南省/益阳市/赫山区",
    "govUrl": "http://www.hnhs.gov.cn/",
    "reason": "no-disclosure-route"
  },
  {
    "key": "湖南省/益阳市/南县",
    "govUrl": "http://www.nanxian.gov.cn/",
    "reason": "no-disclosure-route"
  },
  {
    "key": "湖南省/益阳市/桃江县",
    "govUrl": "http://www.taojiang.gov.cn/",
    "reason": "no-disclosure-route"
  },
  {
    "key": "湖南省/益阳市/沅江市",
    "govUrl": "http://www.yuanjiang.gov.cn/",
    "reason": "no-disclosure-route"
  },
  {
    "key": "湖南省/益阳市/资阳区",
    "govUrl": "http://www.hnziyang.gov.cn/",
    "reason": "no-disclosure-route"
  },
  {
    "key": "湖南省/岳阳市",
    "govUrl": "https://www.yueyang.gov.cn/",
    "reason": "no-disclosure-route"
  },
  {
    "key": "湖南省/岳阳市/华容县",
    "govUrl": "https://www.huarong.gov.cn/",
    "reason": "no-disclosure-route"
  },
  {
    "key": "湖南省/岳阳市/君山区",
    "govUrl": "https://www.junshan.gov.cn/",
    "reason": "no-disclosure-route"
  },
  {
    "key": "湖南省/岳阳市/临湘市",
    "govUrl": "https://www.linxiang.gov.cn/",
    "reason": "no-disclosure-route"
  },
  {
    "key": "湖南省/岳阳市/汨罗市",
    "govUrl": "https://www.miluo.gov.cn/",
    "reason": "no-disclosure-route"
  },
  {
    "key": "湖南省/岳阳市/平江县",
    "govUrl": "https://www.pingjiang.gov.cn/",
    "reason": "no-disclosure-route"
  },
  {
    "key": "湖南省/岳阳市/湘阴县",
    "govUrl": "https://www.xiangyin.gov.cn/",
    "reason": "no-disclosure-route"
  },
  {
    "key": "湖南省/岳阳市/岳阳楼区",
    "govUrl": "https://www.yylq.gov.cn/",
    "reason": "no-disclosure-route"
  },
  {
    "key": "湖南省/岳阳市/岳阳县",
    "govUrl": "https://www.yyx.gov.cn/",
    "reason": "no-disclosure-route"
  },
  {
    "key": "湖南省/岳阳市/云溪区",
    "govUrl": "https://www.yunxiqu.gov.cn/",
    "reason": "no-disclosure-route"
  },
  {
    "key": "湖南省/张家界市/慈利县",
    "govUrl": "http://www.cili.gov.cn/",
    "reason": "no-disclosure-route"
  },
  {
    "key": "湖南省/张家界市/桑植县",
    "govUrl": "http://www.sangzhi.gov.cn/",
    "reason": "no-disclosure-route"
  },
  {
    "key": "湖南省/张家界市/永定区",
    "govUrl": "http://www.zjjyd.gov.cn/",
    "reason": "no-disclosure-route"
  },
  {
    "key": "湖南省/长沙市/芙蓉区",
    "govUrl": "http://www.furong.gov.cn/",
    "picked": {
      "url": "http://www.furong.gov.cn/zt/zwgkzt/",
      "text": "“政务公开主题日”活动",
      "score": 92,
      "source": "anchor",
      "validated": true
    }
  },
  {
    "key": "湖南省/长沙市/宁乡市",
    "govUrl": "http://www.nxcity.gov.cn/",
    "picked": {
      "url": "http://www.nxcity.gov.cn/zw229/",
      "text": "政府信息公开",
      "score": 90,
      "source": "anchor",
      "validated": true
    }
  },
  {
    "key": "湖南省/长沙市/长沙县",
    "govUrl": "http://www.csx.gov.cn/",
    "picked": {
      "url": "http://www.csx.gov.cn/zwgk/",
      "text": "政务公开",
      "score": 92,
      "source": "anchor",
      "validated": true
    }
  },
  {
    "key": "湖南省/株洲市",
    "govUrl": "https://www.zhuzhou.gov.cn/",
    "reason": "no-disclosure-route"
  },
  {
    "key": "湖南省/株洲市/茶陵县",
    "govUrl": "http://www.chaling.gov.cn/",
    "reason": "no-disclosure-route"
  },
  {
    "key": "吉林省/白山市",
    "govUrl": "http://www.cbs.gov.cn/",
    "reason": "no-disclosure-route"
  },
  {
    "key": "吉林省/吉林市/船营区",
    "govUrl": "http://www.jlcy.gov.cn/",
    "reason": "no-disclosure-route"
  },
  {
    "key": "吉林省/延边朝鲜族自治州/延吉市",
    "govUrl": "http://www.yanji.gov.cn/",
    "picked": {
      "url": "http://www.yanji.gov.cn/yjszfxxgkw/",
      "text": "政府信息公开",
      "score": 90,
      "source": "anchor",
      "validated": true
    }
  },
  {
    "key": "吉林省/长春市/农安县",
    "govUrl": "http://www.nongan.gov.cn/",
    "reason": "no-disclosure-route"
  },
  {
    "key": "江苏省/淮安市/金湖县",
    "govUrl": "http://www.jinhu.gov.cn/",
    "reason": "no-disclosure-route"
  },
  {
    "key": "江苏省/连云港市/赣榆区",
    "govUrl": "https://www.ganyu.gov.cn/",
    "reason": "no-disclosure-route"
  },
  {
    "key": "江苏省/南通市/崇川区",
    "govUrl": "https://www.chongchuan.gov.cn/",
    "reason": "no-disclosure-route"
  },
  {
    "key": "江苏省/南通市/如皋市",
    "govUrl": "https://www.rugao.gov.cn/",
    "reason": "no-disclosure-route"
  },
  {
    "key": "江苏省/徐州市/贾汪区",
    "govUrl": "http://www.xzjw.gov.cn/",
    "reason": "no-disclosure-route"
  },
  {
    "key": "江苏省/盐城市/东台市",
    "govUrl": "https://www.dongtai.gov.cn/",
    "reason": "no-disclosure-route"
  },
  {
    "key": "江苏省/盐城市/亭湖区",
    "govUrl": "https://www.tinghu.gov.cn/",
    "reason": "no-disclosure-route"
  },
  {
    "key": "江苏省/盐城市/响水县",
    "govUrl": "https://www.xiangshui.gov.cn/",
    "reason": "no-disclosure-route"
  },
  {
    "key": "江西省/抚州市/东乡区",
    "govUrl": "http://www.jxfzdx.gov.cn/",
    "reason": "no-disclosure-route"
  },
  {
    "key": "江西省/抚州市/金溪县",
    "govUrl": "http://www.jinxi.gov.cn/",
    "reason": "no-disclosure-route"
  },
  {
    "key": "江西省/抚州市/乐安县",
    "govUrl": "http://www.jxlean.gov.cn/",
    "reason": "no-disclosure-route"
  },
  {
    "key": "江西省/抚州市/黎川县",
    "govUrl": "http://www.jxlcx.gov.cn/",
    "reason": "no-disclosure-route"
  },
  {
    "key": "江西省/抚州市/临川区",
    "govUrl": "http://www.jxlc.gov.cn/",
    "reason": "no-disclosure-route"
  },
  {
    "key": "江西省/抚州市/南城县",
    "govUrl": "http://www.jxnc.gov.cn/",
    "reason": "no-disclosure-route"
  },
  {
    "key": "江西省/抚州市/南丰县",
    "govUrl": "http://www.jxnf.gov.cn/",
    "reason": "no-disclosure-route"
  },
  {
    "key": "江西省/抚州市/资溪县",
    "govUrl": "http://www.zixi.gov.cn/",
    "reason": "no-disclosure-route"
  },
  {
    "key": "江西省/吉安市/安福县",
    "govUrl": "http://www.afx.gov.cn/",
    "reason": "no-disclosure-route"
  },
  {
    "key": "江西省/景德镇市",
    "govUrl": "https://www.jdz.gov.cn/",
    "reason": "no-disclosure-route"
  },
  {
    "key": "江西省/景德镇市/昌江区",
    "govUrl": "http://www.jdzcjq.gov.cn/",
    "reason": "no-disclosure-route"
  },
  {
    "key": "江西省/景德镇市/浮梁县",
    "govUrl": "https://fuliang.gov.cn/",
    "reason": "no-disclosure-route"
  },
  {
    "key": "江西省/景德镇市/乐平市",
    "govUrl": "http://www.lps.gov.cn/",
    "reason": "no-disclosure-route"
  },
  {
    "key": "江西省/景德镇市/珠山区",
    "govUrl": "http://www.jdzzsq.gov.cn/",
    "reason": "no-disclosure-route"
  },
  {
    "key": "江西省/九江市/瑞昌市",
    "govUrl": "http://www.ruichang.gov.cn/",
    "reason": "no-disclosure-route"
  },
  {
    "key": "江西省/萍乡市",
    "govUrl": "https://www.pingxiang.gov.cn/",
    "reason": "no-disclosure-route"
  },
  {
    "key": "江西省/萍乡市/安源区",
    "govUrl": "http://www.jxay.gov.cn/",
    "reason": "no-disclosure-route"
  },
  {
    "key": "江西省/萍乡市/莲花县",
    "govUrl": "http://www.zglh.gov.cn/",
    "reason": "no-disclosure-route"
  },
  {
    "key": "江西省/萍乡市/芦溪县",
    "govUrl": "http://www.luxi.gov.cn/",
    "reason": "no-disclosure-route"
  },
  {
    "key": "江西省/萍乡市/上栗县",
    "govUrl": "https://www.jxslx.gov.cn/",
    "reason": "no-disclosure-route"
  },
  {
    "key": "江西省/萍乡市/湘东区",
    "govUrl": "http://www.jxxd.gov.cn/",
    "reason": "no-disclosure-route"
  },
  {
    "key": "江西省/上饶市/德兴市",
    "govUrl": "http://www.dxs.gov.cn/",
    "reason": "no-disclosure-route"
  },
  {
    "key": "江西省/上饶市/弋阳县",
    "govUrl": "http://www.jxyy.gov.cn/",
    "reason": "homepage-unreachable"
  },
  {
    "key": "江西省/上饶市/玉山县",
    "govUrl": "http://www.zgys.gov.cn/",
    "reason": "no-disclosure-route"
  },
  {
    "key": "辽宁省/大连市/金州区",
    "govUrl": "http://www.dljp.gov.cn/",
    "reason": "no-disclosure-route"
  },
  {
    "key": "辽宁省/大连市/沙河口区",
    "govUrl": "http://www.dlshk.gov.cn/",
    "reason": "no-disclosure-route"
  },
  {
    "key": "辽宁省/大连市/西岗区",
    "govUrl": "http://www.dlxg.gov.cn/",
    "reason": "homepage-unreachable"
  },
  {
    "key": "辽宁省/大连市/长海县",
    "govUrl": "https://www.dlch.gov.cn/",
    "reason": "no-disclosure-route"
  },
  {
    "key": "辽宁省/大连市/中山区",
    "govUrl": "http://www.dlzs.gov.cn/",
    "reason": "homepage-unreachable"
  },
  {
    "key": "辽宁省/大连市/庄河市",
    "govUrl": "http://dlzh.gov.cn/",
    "reason": "no-disclosure-route"
  },
  {
    "key": "辽宁省/抚顺市/东洲区",
    "govUrl": "http://www.fsdz.gov.cn/",
    "reason": "no-disclosure-route"
  },
  {
    "key": "辽宁省/抚顺市/新宾满族自治县",
    "govUrl": "http://www.xinbin.gov.cn/",
    "reason": "no-disclosure-route"
  },
  {
    "key": "辽宁省/阜新市/阜新蒙古族自治县",
    "govUrl": "https://www.fmx.gov.cn/",
    "reason": "homepage-unreachable"
  },
  {
    "key": "辽宁省/葫芦岛市/南票区",
    "govUrl": "http://www.npq.gov.cn/",
    "reason": "no-disclosure-route"
  },
  {
    "key": "辽宁省/锦州市/古塔区",
    "govUrl": "http://www.jzgtq.gov.cn/",
    "reason": "no-disclosure-route"
  },
  {
    "key": "辽宁省/辽阳市",
    "govUrl": "http://www.liaoyang.gov.cn/",
    "reason": "no-disclosure-route"
  },
  {
    "key": "内蒙古自治区/阿拉善盟",
    "govUrl": "https://www.als.gov.cn/",
    "reason": "no-disclosure-route"
  },
  {
    "key": "内蒙古自治区/阿拉善盟/额济纳旗",
    "govUrl": "https://www.ejnq.gov.cn/",
    "reason": "no-disclosure-route"
  },
  {
    "key": "内蒙古自治区/巴彦淖尔市/乌拉特中旗",
    "govUrl": "http://www.wltzq.gov.cn/",
    "reason": "homepage-unreachable"
  },
  {
    "key": "内蒙古自治区/赤峰市/克什克腾旗",
    "govUrl": "http://www.kskt.gov.cn/",
    "reason": "homepage-unreachable"
  },
  {
    "key": "内蒙古自治区/锡林郭勒盟/苏尼特右旗",
    "govUrl": "https://www.sntyq.gov.cn/",
    "reason": "homepage-unreachable"
  },
  {
    "key": "宁夏回族自治区/固原市/彭阳县",
    "govUrl": "https://www.pengyang.gov.cn/",
    "reason": "no-disclosure-route"
  },
  {
    "key": "宁夏回族自治区/吴忠市/盐池县",
    "govUrl": "http://www.yanchi.gov.cn/",
    "reason": "no-disclosure-route"
  },
  {
    "key": "青海省/果洛藏族自治州",
    "govUrl": "https://www.guoluo.gov.cn/",
    "reason": "homepage-unreachable"
  },
  {
    "key": "青海省/果洛藏族自治州/班玛县",
    "govUrl": "http://www.banma.gov.cn/",
    "reason": "homepage-unreachable"
  },
  {
    "key": "青海省/果洛藏族自治州/达日县",
    "govUrl": "http://www.dari.gov.cn/",
    "reason": "homepage-unreachable"
  },
  {
    "key": "青海省/果洛藏族自治州/甘德县",
    "govUrl": "http://www.gande.gov.cn/",
    "reason": "homepage-unreachable"
  },
  {
    "key": "青海省/果洛藏族自治州/久治县",
    "govUrl": "http://www.jiuzhixian.gov.cn/",
    "reason": "homepage-unreachable"
  },
  {
    "key": "青海省/果洛藏族自治州/玛多县",
    "govUrl": "http://www.maduo.gov.cn/",
    "reason": "homepage-unreachable"
  },
  {
    "key": "青海省/果洛藏族自治州/玛沁县",
    "govUrl": "http://www.maqin.gov.cn/",
    "reason": "homepage-unreachable"
  },
  {
    "key": "青海省/海东市/化隆回族自治县",
    "govUrl": "http://www.hualongxian.gov.cn/",
    "reason": "homepage-unreachable"
  },
  {
    "key": "青海省/海东市/循化撒拉族自治县",
    "govUrl": "http://www.xunhua.gov.cn/",
    "reason": "no-disclosure-route"
  },
  {
    "key": "青海省/海西蒙古族藏族自治州",
    "govUrl": "https://www.haixi.gov.cn/",
    "reason": "homepage-unreachable"
  },
  {
    "key": "青海省/海西蒙古族藏族自治州/德令哈市",
    "govUrl": "http://www.delingha.gov.cn/",
    "reason": "no-disclosure-route"
  },
  {
    "key": "青海省/海西蒙古族藏族自治州/都兰县",
    "govUrl": "http://www.dulan.gov.cn/",
    "reason": "no-disclosure-route"
  },
  {
    "key": "青海省/海西蒙古族藏族自治州/茫崖市",
    "govUrl": "https://www.mangya.gov.cn/",
    "reason": "no-disclosure-route"
  },
  {
    "key": "青海省/海西蒙古族藏族自治州/天峻县",
    "govUrl": "http://www.tianjun.gov.cn/",
    "reason": "no-disclosure-route"
  },
  {
    "key": "青海省/黄南藏族自治州",
    "govUrl": "http://www.huangnan.gov.cn/",
    "reason": "homepage-unreachable"
  },
  {
    "key": "青海省/黄南藏族自治州/河南蒙古族自治县",
    "govUrl": "http://www.henanxian.gov.cn/",
    "reason": "homepage-unreachable"
  },
  {
    "key": "青海省/西宁市/城西区",
    "govUrl": "https://www.xncx.gov.cn/",
    "reason": "no-disclosure-route"
  },
  {
    "key": "青海省/西宁市/城中区",
    "govUrl": "https://xncz.gov.cn/",
    "reason": "no-disclosure-route"
  },
  {
    "key": "青海省/西宁市/湟源县",
    "govUrl": "https://www.huangyuan.gov.cn/",
    "picked": {
      "url": "https://www.huangyuan.gov.cn/index.php?s=news&c=category&id=53",
      "text": "政府信息公开",
      "score": 90,
      "source": "anchor",
      "validated": true
    }
  },
  {
    "key": "青海省/西宁市/湟中区",
    "govUrl": "https://www.huangzhong.gov.cn/",
    "reason": "no-disclosure-route"
  },
  {
    "key": "山东省/德州市/平原县",
    "govUrl": "http://www.zgpingyuan.gov.cn/",
    "reason": "no-disclosure-route"
  },
  {
    "key": "山东省/东营市/东营区",
    "govUrl": "http://www.dyq.gov.cn/",
    "reason": "no-disclosure-route"
  },
  {
    "key": "山东省/东营市/广饶县",
    "govUrl": "http://www.guangrao.gov.cn/",
    "reason": "no-disclosure-route"
  },
  {
    "key": "山东省/东营市/河口区",
    "govUrl": "http://www.hekou.gov.cn/",
    "reason": "no-disclosure-route"
  },
  {
    "key": "山东省/济南市/历下区",
    "govUrl": "http://www.lixia.gov.cn/",
    "reason": "no-disclosure-route"
  },
  {
    "key": "山东省/济宁市/嘉祥县",
    "govUrl": "http://www.jiaxiang.gov.cn/",
    "reason": "homepage-unreachable"
  },
  {
    "key": "山东省/济宁市/金乡县",
    "govUrl": "http://www.jinxiang.gov.cn/",
    "reason": "homepage-unreachable"
  },
  {
    "key": "山东省/济宁市/曲阜市",
    "govUrl": "http://www.qufu.gov.cn/",
    "reason": "homepage-unreachable"
  },
  {
    "key": "山东省/济宁市/任城区",
    "govUrl": "http://jirczwfw.sd.gov.cn/",
    "reason": "homepage-unreachable"
  },
  {
    "key": "山东省/济宁市/微山县",
    "govUrl": "http://jiwszwfw.sd.gov.cn/",
    "reason": "homepage-unreachable"
  },
  {
    "key": "山东省/济宁市/鱼台县",
    "govUrl": "http://jiytzwfw.sd.gov.cn/",
    "reason": "homepage-unreachable"
  },
  {
    "key": "山东省/聊城市",
    "govUrl": "http://www.liaocheng.gov.cn/",
    "reason": "homepage-unreachable"
  },
  {
    "key": "山东省/临沂市",
    "govUrl": "https://www.linyi.gov.cn/",
    "picked": {
      "url": "https://www.linyi.gov.cn/typt.htm",
      "text": "法定公开内容",
      "score": 75,
      "source": "anchor",
      "validated": true
    }
  },
  {
    "key": "山东省/临沂市/平邑县",
    "govUrl": "http://www.pingyi.gov.cn/",
    "reason": "homepage-unreachable"
  },
  {
    "key": "山东省/临沂市/郯城县",
    "govUrl": "http://www.tancheng.gov.cn/",
    "reason": "no-disclosure-route"
  },
  {
    "key": "山东省/日照市",
    "govUrl": "http://www.rizhao.gov.cn/",
    "reason": "no-disclosure-route"
  },
  {
    "key": "山东省/日照市/五莲县",
    "govUrl": "http://www.wulian.gov.cn/",
    "reason": "no-disclosure-route"
  },
  {
    "key": "山东省/威海市/文登区",
    "govUrl": "http://www.wendeng.gov.cn/",
    "reason": "no-disclosure-route"
  },
  {
    "key": "山东省/枣庄市/峄城区",
    "govUrl": "http://www.ycq.gov.cn/",
    "reason": "no-disclosure-route"
  },
  {
    "key": "山东省/淄博市/高青县",
    "govUrl": "http://www.gaoqing.gov.cn/",
    "reason": "no-disclosure-route"
  },
  {
    "key": "山东省/淄博市/临淄区",
    "govUrl": "http://www.linzi.gov.cn/",
    "reason": "no-disclosure-route"
  },
  {
    "key": "山东省/淄博市/沂源县",
    "govUrl": "http://www.yiyuan.gov.cn/",
    "reason": "no-disclosure-route"
  },
  {
    "key": "山西省/晋中市/平遥县",
    "govUrl": "http://www.pingyao.gov.cn/",
    "reason": "no-disclosure-route"
  },
  {
    "key": "山西省/晋中市/祁县",
    "govUrl": "http://www.qixian.gov.cn/",
    "picked": {
      "url": "http://www.qixian.gov.cn/zwgk/",
      "text": "政务公开",
      "score": 58,
      "source": "constructed",
      "validated": true
    }
  },
  {
    "key": "山西省/晋中市/榆社县",
    "govUrl": "http://www.yushe.gov.cn/",
    "reason": "homepage-unreachable"
  },
  {
    "key": "山西省/晋中市/左权县",
    "govUrl": "http://www.jzzq.gov.cn/",
    "reason": "homepage-unreachable"
  },
  {
    "key": "山西省/吕梁市/岚县",
    "govUrl": "http://www.lanxian.gov.cn/",
    "reason": "homepage-unreachable"
  },
  {
    "key": "山西省/太原市/尖草坪区",
    "govUrl": "https://www.tyjcp.gov.cn/",
    "reason": "no-disclosure-route"
  },
  {
    "key": "山西省/太原市/娄烦县",
    "govUrl": "https://www.sxlf.gov.cn/",
    "reason": "no-disclosure-route"
  },
  {
    "key": "山西省/太原市/万柏林区",
    "govUrl": "https://www.sxtywbl.gov.cn/",
    "reason": "no-disclosure-route"
  },
  {
    "key": "山西省/太原市/杏花岭区",
    "govUrl": "https://www.sxtyxhl.gov.cn/",
    "reason": "homepage-unreachable"
  },
  {
    "key": "山西省/阳泉市/城区",
    "govUrl": "http://www.yqcq.gov.cn/",
    "reason": "no-disclosure-route"
  },
  {
    "key": "山西省/阳泉市/郊区",
    "govUrl": "http://www.yqjq.gov.cn/",
    "reason": "no-disclosure-route"
  },
  {
    "key": "山西省/运城市/夏县",
    "govUrl": "https://www.sxxiaxian.gov.cn/",
    "reason": "homepage-unreachable"
  },
  {
    "key": "山西省/长治市/潞州区",
    "govUrl": "http://www.luzhouqu.gov.cn/",
    "reason": "no-disclosure-route"
  },
  {
    "key": "陕西省/宝鸡市/金台区",
    "govUrl": "http://www.jintai.gov.cn/",
    "reason": "no-disclosure-route"
  },
  {
    "key": "陕西省/宝鸡市/太白县",
    "govUrl": "http://www.taibai.gov.cn/",
    "reason": "no-disclosure-route"
  },
  {
    "key": "陕西省/铜川市/印台区",
    "govUrl": "http://www.yintai.gov.cn/",
    "reason": "homepage-unreachable"
  },
  {
    "key": "陕西省/渭南市/韩城市",
    "govUrl": "http://www.hancheng.gov.cn/",
    "reason": "homepage-unreachable"
  },
  {
    "key": "陕西省/渭南市/华州区",
    "govUrl": "https://www.hzqu.gov.cn/",
    "reason": "no-disclosure-route"
  },
  {
    "key": "陕西省/咸阳市/旬邑县",
    "govUrl": "http://www.snxunyi.gov.cn/",
    "reason": "no-disclosure-route"
  },
  {
    "key": "陕西省/延安市",
    "govUrl": "http://www.yanan.gov.cn/",
    "reason": "no-disclosure-route"
  },
  {
    "key": "陕西省/榆林市/神木市",
    "govUrl": "https://www.sxsm.gov.cn/",
    "reason": "no-disclosure-route"
  },
  {
    "key": "上海市/闵行区",
    "govUrl": "https://www.shmh.gov.cn/",
    "reason": "no-disclosure-route"
  },
  {
    "key": "四川省/成都市/成华区",
    "govUrl": "http://www.chenghua.gov.cn/",
    "reason": "homepage-unreachable"
  },
  {
    "key": "四川省/成都市/崇州市",
    "govUrl": "http://www.chongzhou.gov.cn/",
    "reason": "homepage-unreachable"
  },
  {
    "key": "四川省/成都市/大邑县",
    "govUrl": "http://www.day.gov.cn/",
    "reason": "homepage-unreachable"
  },
  {
    "key": "四川省/成都市/都江堰市",
    "govUrl": "http://www.djy.gov.cn/",
    "reason": "homepage-unreachable"
  },
  {
    "key": "四川省/成都市/简阳市",
    "govUrl": "http://www.scjy.gov.cn/",
    "reason": "homepage-unreachable"
  },
  {
    "key": "四川省/成都市/金牛区",
    "govUrl": "http://www.jinniu.gov.cn/",
    "reason": "homepage-unreachable"
  },
  {
    "key": "四川省/成都市/金堂县",
    "govUrl": "http://www.jintang.gov.cn/",
    "reason": "homepage-unreachable"
  },
  {
    "key": "四川省/成都市/锦江区",
    "govUrl": "http://www.cdjinjiang.gov.cn/",
    "reason": "homepage-unreachable"
  },
  {
    "key": "四川省/成都市/龙泉驿区",
    "govUrl": "http://www.longquanyi.gov.cn/",
    "reason": "homepage-unreachable"
  },
  {
    "key": "四川省/成都市/彭州市",
    "govUrl": "http://www.pengzhou.gov.cn/",
    "reason": "homepage-unreachable"
  },
  {
    "key": "四川省/成都市/郫都区",
    "govUrl": "http://www.pidu.gov.cn/",
    "reason": "homepage-unreachable"
  },
  {
    "key": "四川省/成都市/蒲江县",
    "govUrl": "http://www.pujiang.gov.cn/",
    "reason": "homepage-unreachable"
  },
  {
    "key": "四川省/成都市/青白江区",
    "govUrl": "http://www.qbj.gov.cn/",
    "reason": "homepage-unreachable"
  },
  {
    "key": "四川省/成都市/青羊区",
    "govUrl": "http://www.cdqingyang.gov.cn/",
    "reason": "homepage-unreachable"
  },
  {
    "key": "四川省/成都市/邛崃市",
    "govUrl": "http://www.qionglai.gov.cn/",
    "reason": "homepage-unreachable"
  },
  {
    "key": "四川省/成都市/双流区",
    "govUrl": "http://www.shuangliu.gov.cn/",
    "reason": "homepage-unreachable"
  },
  {
    "key": "四川省/成都市/温江区",
    "govUrl": "http://www.wenjiang.gov.cn/",
    "reason": "homepage-unreachable"
  },
  {
    "key": "四川省/成都市/武侯区",
    "govUrl": "http://www.cdwh.gov.cn/",
    "reason": "homepage-unreachable"
  },
  {
    "key": "四川省/成都市/新都区",
    "govUrl": "http://www.xindu.gov.cn/",
    "reason": "homepage-unreachable"
  },
  {
    "key": "四川省/成都市/新津区",
    "govUrl": "http://www.xinjin.gov.cn/",
    "reason": "homepage-unreachable"
  },
  {
    "key": "四川省/达州市/大竹县",
    "govUrl": "http://www.dazhu.gov.cn/",
    "reason": "homepage-unreachable"
  },
  {
    "key": "四川省/广安市/武胜县",
    "govUrl": "https://www.wusheng.gov.cn/",
    "reason": "no-disclosure-route"
  },
  {
    "key": "四川省/广安市/岳池县",
    "govUrl": "https://www.scyc.gov.cn/",
    "reason": "no-disclosure-route"
  },
  {
    "key": "四川省/广元市",
    "govUrl": "http://www.cngy.gov.cn/",
    "reason": "homepage-unreachable"
  },
  {
    "key": "四川省/广元市/朝天区",
    "govUrl": "http://www.gyct.gov.cn/",
    "reason": "homepage-unreachable"
  },
  {
    "key": "四川省/广元市/剑阁县",
    "govUrl": "http://www.cnjg.gov.cn/",
    "reason": "homepage-unreachable"
  },
  {
    "key": "四川省/广元市/利州区",
    "govUrl": "https://www.lzq.gov.cn/",
    "reason": "homepage-unreachable"
  },
  {
    "key": "四川省/广元市/青川县",
    "govUrl": "http://www.cnqc.gov.cn/",
    "reason": "homepage-unreachable"
  },
  {
    "key": "四川省/广元市/旺苍县",
    "govUrl": "http://www.scgw.gov.cn/",
    "reason": "homepage-unreachable"
  },
  {
    "key": "四川省/广元市/昭化区",
    "govUrl": "https://www.cnzh.gov.cn/",
    "reason": "homepage-unreachable"
  },
  {
    "key": "四川省/乐山市/沙湾区",
    "govUrl": "http://www.shawan.gov.cn/",
    "reason": "no-disclosure-route"
  },
  {
    "key": "四川省/绵阳市/安州区",
    "govUrl": "http://www.anzhou.gov.cn/",
    "reason": "no-disclosure-route"
  },
  {
    "key": "四川省/雅安市",
    "govUrl": "http://www.yaan.gov.cn/",
    "reason": "homepage-unreachable"
  },
  {
    "key": "西藏自治区/拉萨市/城关区",
    "govUrl": "https://www.cgq.gov.cn/",
    "picked": {
      "url": "https://www.cgq.gov.cn/cgqrmzf/zwgk/zwgk.shtml",
      "text": "政务公开",
      "score": 92,
      "source": "anchor",
      "validated": true
    }
  },
  {
    "key": "西藏自治区/那曲市/聂荣县",
    "govUrl": "http://www.nqnrx.gov.cn/",
    "reason": "no-disclosure-route"
  },
  {
    "key": "新疆维吾尔自治区/阿克苏地区/拜城县",
    "govUrl": "https://www.xjbc.gov.cn/",
    "reason": "homepage-unreachable"
  },
  {
    "key": "新疆维吾尔自治区/博尔塔拉蒙古自治州/博乐市",
    "govUrl": "http://www.xjbl.gov.cn/",
    "reason": "homepage-unreachable"
  },
  {
    "key": "新疆维吾尔自治区/博尔塔拉蒙古自治州/温泉县",
    "govUrl": "http://www.xjwq.gov.cn/",
    "reason": "homepage-unreachable"
  },
  {
    "key": "新疆维吾尔自治区/喀什地区/英吉沙县",
    "govUrl": "http://www.yjs.gov.cn/",
    "reason": "no-disclosure-route"
  },
  {
    "key": "新疆维吾尔自治区/克孜勒苏柯尔克孜自治州/阿合奇县",
    "govUrl": "https://www.xjahq.gov.cn/",
    "reason": "no-disclosure-route"
  },
  {
    "key": "新疆维吾尔自治区/克孜勒苏柯尔克孜自治州/乌恰县",
    "govUrl": "http://www.xjwqx.gov.cn/",
    "reason": "no-disclosure-route"
  },
  {
    "key": "新疆维吾尔自治区/乌鲁木齐市/米东区",
    "govUrl": "http://www.xjmd.gov.cn/",
    "picked": {
      "url": "http://www.xjmd.gov.cn/info/content.jsp?node_id=GKrm&info_id=7895&tm_id=68&q=xxgkzn",
      "text": "政府信息公开",
      "score": 90,
      "source": "anchor",
      "validated": true
    }
  },
  {
    "key": "新疆维吾尔自治区/新疆生产建设兵团/白杨市",
    "govUrl": "https://www.btdjs.gov.cn/",
    "reason": "no-disclosure-route"
  },
  {
    "key": "云南省/红河哈尼族彝族自治州/石屏县",
    "govUrl": "https://hhsp.gov.cn/",
    "reason": "homepage-unreachable"
  },
  {
    "key": "云南省/红河哈尼族彝族自治州/元阳县",
    "govUrl": "https://www.hhyy.gov.cn/",
    "reason": "no-disclosure-route"
  },
  {
    "key": "云南省/昆明市/五华区",
    "govUrl": "http://www.kmwh.gov.cn/",
    "reason": "no-disclosure-route"
  },
  {
    "key": "云南省/临沧市/耿马傣族佤族自治县",
    "govUrl": "http://www.yngm.gov.cn/",
    "reason": "homepage-unreachable"
  },
  {
    "key": "云南省/临沧市/双江拉祜族佤族布朗族傣族自治县",
    "govUrl": "https://www.shuangjiang.gov.cn/",
    "reason": "homepage-unreachable"
  },
  {
    "key": "云南省/临沧市/云县",
    "govUrl": "http://www.ynyx.gov.cn/",
    "reason": "homepage-unreachable"
  },
  {
    "key": "云南省/普洱市",
    "govUrl": "https://www.puershi.gov.cn/",
    "reason": "homepage-unreachable"
  },
  {
    "key": "云南省/文山壮族苗族自治州/富宁县",
    "govUrl": "https://www.ynfn.gov.cn/",
    "reason": "homepage-unreachable"
  },
  {
    "key": "云南省/文山壮族苗族自治州/麻栗坡县",
    "govUrl": "http://www.ynmlp.gov.cn/",
    "reason": "homepage-unreachable"
  },
  {
    "key": "云南省/文山壮族苗族自治州/丘北县",
    "govUrl": "http://www.ynqb.gov.cn/",
    "reason": "homepage-unreachable"
  },
  {
    "key": "云南省/文山壮族苗族自治州/文山市",
    "govUrl": "http://www.ynwss.gov.cn/",
    "reason": "homepage-unreachable"
  },
  {
    "key": "云南省/文山壮族苗族自治州/西畴县",
    "govUrl": "https://www.xczw.gov.cn/",
    "reason": "homepage-unreachable"
  },
  {
    "key": "云南省/文山壮族苗族自治州/砚山县",
    "govUrl": "http://www.yanshan.gov.cn/",
    "reason": "homepage-unreachable"
  },
  {
    "key": "云南省/西双版纳傣族自治州/勐腊县",
    "govUrl": "https://www.ynml.gov.cn/",
    "reason": "homepage-unreachable"
  },
  {
    "key": "云南省/昭通市/巧家县",
    "govUrl": "http://www.qiaojia.gov.cn/",
    "reason": "homepage-unreachable"
  },
  {
    "key": "浙江省/金华市",
    "govUrl": "https://www.jinhua.gov.cn/",
    "reason": "no-disclosure-route"
  },
  {
    "key": "浙江省/丽水市/云和县",
    "govUrl": "http://www.yunhe.gov.cn/",
    "reason": "no-disclosure-route"
  },
  {
    "key": "浙江省/衢州市/常山县",
    "govUrl": "https://www.zjcs.gov.cn/",
    "reason": "no-disclosure-route"
  },
  {
    "key": "浙江省/衢州市/开化县",
    "govUrl": "https://www.kaihua.gov.cn/",
    "reason": "no-disclosure-route"
  },
  {
    "key": "浙江省/衢州市/衢江区",
    "govUrl": "https://www.qjq.gov.cn/",
    "reason": "no-disclosure-route"
  },
  {
    "key": "浙江省/台州市",
    "govUrl": "https://www.zjtz.gov.cn/",
    "reason": "no-disclosure-route"
  },
  {
    "key": "浙江省/台州市/黄岩区",
    "govUrl": "https://www.zjhy.gov.cn/",
    "reason": "no-disclosure-route"
  },
  {
    "key": "浙江省/台州市/临海市",
    "govUrl": "https://www.linhai.gov.cn/",
    "reason": "no-disclosure-route"
  },
  {
    "key": "浙江省/温州市",
    "govUrl": "https://www.wenzhou.gov.cn/",
    "reason": "no-disclosure-route"
  },
  {
    "key": "浙江省/温州市/乐清市",
    "govUrl": "https://www.yueqing.gov.cn/",
    "reason": "no-disclosure-route"
  },
  {
    "key": "浙江省/温州市/瑞安市",
    "govUrl": "http://www.ruian.gov.cn/",
    "reason": "no-disclosure-route"
  }
]